pyidebug
